[{
		"id": 1,
		"name": "Терминатор",
		"nameOrig": "The Terminator",
		"genres": ["movie-foreign"],
		"year": "1984"
	},
	{
		"id": 2,
		"name": "Властелин колец: Братство кольца",
		"nameOrig": "The Lord of the Rings: The Fellowship of the Ring",
		"genres": ["movie-foreign"],
		"year": "2001"
	},
	{
		"id": 3,
		"name": "Титаник",
		"nameOrig": "Titanic",
		"genres": ["movie-foreign"],
		"year": "1997"
	},
	{
		"id": 4,
		"name": "Зеленая миля",
		"nameOrig": "The Green Mile",
		"genres": ["movie-foreign"],
		"year": "1999"
	},
	{
		"id": 5,
		"name": "Терминатор 2: Судный день",
		"nameOrig": "Terminator 2: Judgment Day",
		"genres": ["movie-foreign"],
		"year": "1991"
	},
	{
		"id": 6,
		"name": "Брат 2",
		"nameOrig": "Брат 2",
		"genres": ["movie-russian"],
		"year": "2000"
	},
	{
		"id": 7,
		"name": "Книга джунглей",
		"nameOrig": "The Jungle Book",
		"genres": ["cartoon-foreign"],
		"year": "1967"
	},
	{
		"id": 8,
		"name": "Жмурки",
		"nameOrig": "Жмурки",
		"genres": ["movie-russian"],
		"year": "2005"
	},
	{
		"id": 9,
		"name": "В поисках Немо",
		"nameOrig": "Finding Nemo",
		"genres": ["cartoon-foreign"],
		"year": "2003"
	},
	{
		"id": 10,
		"name": "ВАЛЛ·И",
		"nameOrig": "WALL·E",
		"genres": ["cartoon-foreign"],
		"year": "2008"
	},
	{
		"id": 11,
		"name": "История игрушек 2",
		"nameOrig": "Toy Story 2",
		"genres": ["cartoon-foreign"],
		"year": "1999"
	},
	{
		"id": 12,
		"name": "Тайна Коко",
		"nameOrig": "Coco",
		"genres": ["cartoon-foreign"],
		"year": "2017"
	},
	{
		"id": 13,
		"name": "Клиника",
		"nameOrig": "Scrubs",
		"genres": ["series-foreign"],
		"year": "2001 - 2010"
	},
	{
		"id": 14,
		"name": "Офис",
		"nameOrig": "The Office",
		"genres": ["series-foreign"],
		"year": "2005 - 2013"
	},
	{
		"id": 15,
		"name": "Во все тяжкие",
		"nameOrig": "Breaking Bad",
		"genres": ["series-foreign"],
		"year": "2008 - 2013"
	},
	{
		"id": 16,
		"name": "Друзья",
		"nameOrig": "Friends",
		"genres": ["series-foreign"],
		"year": "1994 - 2004"
	},
	{
		"id": 17,
		"name": "Как я встретил вашу маму",
		"nameOrig": "How I Met Your Mother",
		"genres": ["series-foreign"],
		"year": "2005 - 2014"
	},
	{
		"id": 18,
		"name": "Теория большого взрыва",
		"nameOrig": "The Big Bang Theory",
		"genres": ["series-foreign"],
		"year": "2007 - 2019"
	},
	{
		"id": 19,
		"name": "Доктор Хаус",
		"nameOrig": "House, M.D.",
		"genres": ["series-foreign"],
		"year": "2004 - 2012"
	},
	{
		"id": 20,
		"name": "Обмани меня",
		"nameOrig": "Lie to Me",
		"genres": ["series-foreign"],
		"year": "2009 - 2011"
	},
	{
		"id": 21,
		"name": "Игра в кальмара",
		"nameOrig": "Ojingeo geim",
		"genres": ["series-foreign"],
		"year": "2021"
	},
	{
		"id": 22,
		"name": "Паразиты",
		"nameOrig": "Gisaengchung",
		"genres": ["movie-foreign"],
		"year": "2019"
	},
	{
		"id": 23,
		"name": "Паранойя",
		"nameOrig": "Disturbia",
		"genres": ["movie-foreign"],
		"year": "2007"
	},
	{
		"id": 24,
		"name": "Мулан",
		"nameOrig": "Mulan",
		"genres": ["cartoon-foreign"],
		"year": "1998"
	},
	{
		"id": 25,
		"name": "Сиротский Бруклин",
		"nameOrig": "Motherless Brooklyn",
		"genres": ["movie-foreign"],
		"year": "2019"
	},
	{
		"id": 26,
		"name": "Ла-Ла Ленд",
		"nameOrig": "La La Land",
		"genres": ["movie-foreign"],
		"year": "2016"
	},
	{
		"id": 27,
		"name": "Приключения Флика",
		"nameOrig": "A Bug's Life",
		"genres": ["cartoon-foreign"],
		"year": "1998"
	},
	{
		"id": 28,
		"name": "Моана",
		"nameOrig": "Moana",
		"genres": ["cartoon-foreign"],
		"year": "2016"
	},
	{
		"id": 29,
		"name": "Манчестер у моря",
		"nameOrig": "Manchester by the Sea",
		"genres": ["movie-foreign"],
		"year": "2016"
	},
	{
		"id": 30,
		"name": "Человек-паук",
		"nameOrig": "Spider-Man",
		"genres": ["movie-foreign"],
		"year": "2002"
	},
	{
		"id": 31,
		"name": "Меняющие реальность",
		"nameOrig": "The Adjustment Bureau",
		"genres": ["movie-foreign"],
		"year": "2011"
	},
	{
		"id": 32,
		"name": "Интерстеллар",
		"nameOrig": "Interstellar",
		"genres": ["movie-foreign"],
		"year": "2014"
	},
	{
		"id": 33,
		"name": "Оно",
		"nameOrig": "It",
		"genres": ["movie-foreign"],
		"year": "2017"
	},
	{
		"id": 34,
		"name": "Тайлер Рейк: Операция по спасению",
		"nameOrig": "Extraction",
		"genres": ["movie-foreign"],
		"year": "2020"
	},
	{
		"id": 35,
		"name": "Один дома",
		"nameOrig": "Home Alone",
		"genres": ["movie-foreign"],
		"year": "1990"
	},
	{
		"id": 36,
		"name": "Матрица",
		"nameOrig": "The Matrix",
		"genres": ["movie-foreign"],
		"year": "1999"
	},
	{
		"id": 37,
		"name": "Лабиринт Фавна",
		"nameOrig": "El laberinto del fauno",
		"genres": ["movie-foreign"],
		"year": "2006"
	},
	{
		"id": 38,
		"name": "Руби Спаркс",
		"nameOrig": "Ruby Sparks",
		"genres": ["movie-foreign"],
		"year": "2012"
	},
	{
		"id": 39,
		"name": "Люди в черном 2",
		"nameOrig": "Men in Black II",
		"genres": ["movie-foreign"],
		"year": "2002"
	},
	{
		"id": 40,
		"name": "Запах женщины",
		"nameOrig": "Scent of a Woman",
		"genres": ["movie-foreign"],
		"year": "1992"
	},
	{
		"id": 41,
		"name": "11.22.63",
		"nameOrig": "11.22.63",
		"genres": ["series-foreign"],
		"year": "2016"
	},
	{
		"id": 42,
		"name": "Крепкий орешек",
		"nameOrig": "Die Hard",
		"genres": ["movie-foreign"],
		"year": "1988"
	},
	{
		"id": 43,
		"name": "Я шагаю по Москве",
		"nameOrig": "Я шагаю по Москве",
		"genres": ["movie-soviet"],
		"year": "1963"
	},
	{
		"id": 44,
		"name": "Курьер",
		"nameOrig": "Курьер",
		"genres": ["movie-soviet"],
		"year": "1986"
	},
	{
		"id": 45,
		"name": "Афоня",
		"nameOrig": "Афоня",
		"genres": ["movie-soviet"],
		"year": "1975"
	},
	{
		"id": 46,
		"name": "Служебный роман",
		"nameOrig": "Служебный роман",
		"genres": ["movie-soviet"],
		"year": "1977"
	},
	{
		"id": 47,
		"name": "9 рота",
		"nameOrig": "9 рота",
		"genres": ["movie-russian"],
		"year": "2005"
	},
	{
		"id": 48,
		"name": "Ночной дозор",
		"nameOrig": "Ночной дозор",
		"genres": ["movie-russian"],
		"year": "2004"
	},
	{
		"id": 49,
		"name": "Выкрутасы",
		"nameOrig": "Выкрутасы",
		"genres": ["movie-russian"],
		"year": "2010"
	},
	{
		"id": 50,
		"name": "Дурак",
		"nameOrig": "Дурак",
		"genres": ["movie-russian"],
		"year": "2014"
	},
	{
		"id": 51,
		"name": "Кавказская пленница",
		"nameOrig": "Кавказская пленница",
		"genres": ["movie-soviet"],
		"year": "1966"
	},
	{
		"id": 52,
		"name": "Девчата",
		"nameOrig": "Девчата",
		"genres": ["movie-soviet"],
		"year": "1962"
	},
	{
		"id": 53,
		"name": "За спичками",
		"nameOrig": "За спичками",
		"genres": ["movie-soviet"],
		"year": "1980"
	},
	{
		"id": 54,
		"name": "Старики-разбойники",
		"nameOrig": "Старики-разбойники",
		"genres": ["movie-soviet"],
		"year": "1971"
	},
	{
		"id": 55,
		"name": "Геймер",
		"nameOrig": "Gamer",
		"genres": ["movie-foreign"],
		"year": "2009"
	},
	{
		"id": 56,
		"name": "Декстер",
		"nameOrig": "Dexter",
		"genres": ["series-foreign"],
		"year": "2006 - 2013"
	},
	{
		"id": 57,
		"name": "ЖАRА",
		"nameOrig": "ЖАRА",
		"genres": ["movie-russian"],
		"year": "2006"
	},
	{
		"id": 58,
		"name": "Питер FM",
		"nameOrig": "Питер FM",
		"genres": ["movie-russian"],
		"year": "2006"
	},
	{
		"id": 59,
		"name": "Ёлки",
		"nameOrig": "Ёлки",
		"genres": ["movie-russian"],
		"year": "2010"
	},
	{
		"id": 60,
		"name": "Голая правда",
		"nameOrig": "The Ugly Truth",
		"genres": ["movie-foreign"],
		"year": "2009"
	},
	{
		"id": 61,
		"name": "Джентльмены",
		"nameOrig": "The Gentlemen",
		"genres": ["movie-foreign"],
		"year": "2019"
	},
	{
		"id": 62,
		"name": "Гарри Поттер и узник Азкабана",
		"nameOrig": "Harry Potter and the Prisoner of Azkaban",
		"genres": ["movie-foreign"],
		"year": "2004"
	},
	{
		"id": 63,
		"name": "Эта дурацкая любовь",
		"nameOrig": "Crazy, Stupid, Love.",
		"genres": ["movie-foreign"],
		"year": "2011"
	},
	{
		"id": 64,
		"name": "Хулиганы",
		"nameOrig": "Hooligans",
		"genres": ["movie-foreign"],
		"year": "2005"
	},
	{
		"id": 65,
		"name": "Отступники",
		"nameOrig": "The Departed",
		"genres": ["movie-foreign"],
		"year": "2006"
	},
	{
		"id": 66,
		"name": "Час пик 3",
		"nameOrig": "Rush Hour 3",
		"genres": ["movie-foreign"],
		"year": "2007"
	},
	{
		"id": 67,
		"name": "Счастье в конверте",
		"nameOrig": "Счастье в конверте",
		"genres": ["movie-russian"],
		"year": "2019"
	},
	{
		"id": 68,
		"name": "Хэппи-энд",
		"nameOrig": "Хэппи-энд",
		"genres": ["movie-russian"],
		"year": "2020"
	},
	{
		"id": 69,
		"name": "Мой сосед Тоторо",
		"nameOrig": "Tonari no Totoro",
		"genres": ["cartoon-foreign"],
		"year": "1988"
	},
	{
		"id": 70,
		"name": "Ходячий замок",
		"nameOrig": "Howl no Ugoku Shiro",
		"genres": ["cartoon-foreign"],
		"year": "2004"
	},
	{
		"id": 71,
		"name": "Ледниковый период",
		"nameOrig": "Ice Age",
		"genres": ["cartoon-foreign"],
		"year": "2002"
	},
	{
		"id": 72,
		"name": "Рио",
		"nameOrig": "Rio",
		"genres": ["cartoon-foreign"],
		"year": "2011"
	},
	{
		"id": 73,
		"name": "Аватар",
		"nameOrig": "Avatar",
		"genres": ["movie-foreign"],
		"year": "2009"
	},
	{
		"id": 74,
		"name": "Славные парни",
		"nameOrig": "Goodfellas",
		"genres": ["movie-foreign"],
		"year": "1990"
	},
	{
		"id": 75,
		"name": "Крысиные бега",
		"nameOrig": "Rat Race",
		"genres": ["movie-foreign"],
		"year": "2001"
	},
	{
		"id": 76,
		"name": "Эффект бабочки",
		"nameOrig": "The Butterfly Effect",
		"genres": ["movie-foreign"],
		"year": "2003"
	},
	{
		"id": 77,
		"name": "Одержимость",
		"nameOrig": "Whiplash",
		"genres": ["movie-foreign"],
		"year": "2013"
	},
	{
		"id": 78,
		"name": "Альфа Дог",
		"nameOrig": "Alpha Dog",
		"genres": ["movie-foreign"],
		"year": "2005"
	},
	{
		"id": 79,
		"name": "В диких условиях",
		"nameOrig": "Into the Wild",
		"genres": ["movie-foreign"],
		"year": "2007"
	},
	{
		"id": 80,
		"name": "Железный человек",
		"nameOrig": "Iron Man",
		"genres": ["movie-foreign"],
		"year": "2008"
	},
	{
		"id": 81,
		"name": "Рататуй",
		"nameOrig": "Ratatouille",
		"genres": ["cartoon-foreign"],
		"year": "2007"
	},
	{
		"id": 82,
		"name": "Корпорация монстров",
		"nameOrig": "Monsters, Inc.",
		"genres": ["cartoon-foreign"],
		"year": "2001"
	},
	{
		"id": 83,
		"name": "Зверополис",
		"nameOrig": "Zootopia",
		"genres": ["cartoon-foreign"],
		"year": "2016"
	},
	{
		"id": 84,
		"name": "Вверх",
		"nameOrig": "Up",
		"genres": ["cartoon-foreign"],
		"year": "2009"
	},
	{
		"id": 85,
		"name": "Головоломка",
		"nameOrig": "Inside Out",
		"genres": ["cartoon-foreign"],
		"year": "2015"
	},
	{
		"id": 86,
		"name": "Бриллиантовая рука",
		"nameOrig": "Бриллиантовая рука",
		"genres": ["movie-soviet"],
		"year": "1968"
	},
	{
		"id": 87,
		"name": "Человек-паук: Через вселенные",
		"nameOrig": "Spider-Man: Into the Spider-Verse",
		"genres": ["cartoon-foreign"],
		"year": "2018"
	},
	{
		"id": 88,
		"name": "Война",
		"nameOrig": "Война",
		"genres": ["movie-russian"],
		"year": "2002"
	},
	{
		"id": 89,
		"name": "Достать ножи",
		"nameOrig": "Knives Out",
		"genres": ["movie-foreign"],
		"year": "2019"
	},
	{
		"id": 90,
		"name": "Человек дождя",
		"nameOrig": "Rain Man",
		"genres": ["movie-foreign"],
		"year": "1988"
	},
	{
		"id": 91,
		"name": "Стражи галактики",
		"nameOrig": "Guardians of the Galaxy",
		"genres": ["movie-foreign"],
		"year": "2014"
	},
	{
		"id": 92,
		"name": "Гран Торино",
		"nameOrig": "Gran Torino",
		"genres": ["movie-foreign"],
		"year": "2008"
	},
	{
		"id": 93,
		"name": "Сапожник",
		"nameOrig": "The Cobbler",
		"genres": ["movie-foreign"],
		"year": "2014"
	},
	{
		"id": 94,
		"name": "Монстры на каникулах",
		"nameOrig": "Hotel Transylvania",
		"genres": ["cartoon-foreign"],
		"year": "2012"
	},
	{
		"id": 95,
		"name": "Трасса 60",
		"nameOrig": "Interstate 60",
		"genres": ["movie-foreign"],
		"year": "2001"
	},
	{
		"id": 96,
		"name": "Гарри Поттер и Тайная комната",
		"nameOrig": "Harry Potter and the Chamber of Secrets",
		"genres": ["movie-foreign"],
		"year": "2002"
	},
	{
		"id": 97,
		"name": "Коммандос",
		"nameOrig": "Commando",
		"genres": ["movie-foreign"],
		"year": "1985"
	},
	{
		"id": 98,
		"name": "Скалолаз",
		"nameOrig": "Cliffhanger",
		"genres": ["movie-foreign"],
		"year": "1993"
	},
	{
		"id": 99,
		"name": "Джон Уик",
		"nameOrig": "John Wick",
		"genres": ["movie-foreign"],
		"year": "2014"
	},
	{
		"id": 100,
		"name": "Крепкий орешек 4.0",
		"nameOrig": "Live Free or Die Hard",
		"genres": ["movie-foreign"],
		"year": "2007"
	},
	{
		"id": 101,
		"name": "Зеленая книга",
		"nameOrig": "Green Book",
		"genres": ["movie-foreign"],
		"year": "2018"
	},
	{
		"id": 102,
		"name": "Призрак",
		"nameOrig": "Призрак",
		"genres": ["movie-russian"],
		"year": "2015"
	},
	{
		"id": 103,
		"name": "Мёд в голове",
		"nameOrig": "Honig im Kopf",
		"genres": ["movie-foreign"],
		"year": "2014"
	},
	{
		"id": 104,
		"name": "Опасная иллюзия",
		"nameOrig": "The Necessary Death of Charlie Countryman",
		"genres": ["movie-foreign"],
		"year": "2013"
	},
	{
		"id": 105,
		"name": "Последний богатырь",
		"nameOrig": "Последний богатырь",
		"genres": ["movie-russian"],
		"year": "2017"
	},
	{
		"id": 106,
		"name": "Игра",
		"nameOrig": "The Game",
		"genres": ["movie-foreign"],
		"year": "1997"
	},
	{
		"id": 107,
		"name": "Адвокат дьявола",
		"nameOrig": "The Devil's Advocate",
		"genres": ["movie-foreign"],
		"year": "1997"
	},
	{
		"id": 108,
		"name": "Парень с нашего кладбища",
		"nameOrig": "Парень с нашего кладбища",
		"genres": ["movie-russian"],
		"year": "2015"
	},
	{
		"id": 109,
		"name": "Как приручить дракона",
		"nameOrig": "How to Train Your Dragon",
		"genres": ["cartoon-foreign"],
		"year": "2010"
	},
	{
		"id": 110,
		"name": "Ну, погоди!",
		"nameOrig": "Ну, погоди!",
		"genres": ["cartoon-soviet"],
		"year": "1969"
	},
	{
		"id": 111,
		"name": "Приключения кота Леопольда",
		"nameOrig": "Приключения кота Леопольда",
		"genres": ["cartoon-soviet"],
		"year": "1975"
	},
	{
		"id": 112,
		"name": "Жил-был пёс",
		"nameOrig": "Жил-был пёс",
		"genres": ["cartoon-soviet"],
		"year": "1982"
	},
	{
		"id": 113,
		"name": "Шайбу! Шайбу!",
		"nameOrig": "Шайбу! Шайбу!",
		"genres": ["cartoon-soviet"],
		"year": "1964"
	},
	{
		"id": 114,
		"name": "Мирный воин",
		"nameOrig": "Peaceful Warrior",
		"genres": ["movie-foreign"],
		"year": "2006"
	},
	{
		"id": 115,
		"name": "Арахисовый сокол",
		"nameOrig": "The Peanut Butter Falcon",
		"genres": ["movie-foreign"],
		"year": "2019"
	},
	{
		"id": 116,
		"name": "Незваные гости",
		"nameOrig": "Wedding Crashers",
		"genres": ["movie-foreign"],
		"year": "2005"
	},
	{
		"id": 117,
		"name": "А вот и Полли",
		"nameOrig": "Along Came Polly",
		"genres": ["movie-foreign"],
		"year": "2004"
	},
	{
		"id": 118,
		"name": "Рок-н-рольщик",
		"nameOrig": "RocknRolla",
		"genres": ["movie-foreign"],
		"year": "2008"
	},
	{
		"id": 119,
		"name": "Великий Гэтсби",
		"nameOrig": "The Great Gatsby",
		"genres": ["movie-foreign"],
		"year": "2013"
	},
	{
		"id": 120,
		"name": "Ford против Ferrari",
		"nameOrig": "Ford v Ferrari",
		"genres": ["movie-foreign"],
		"year": "2019"
	},
	{
		"id": 121,
		"name": "Изгой",
		"nameOrig": "Cast Away",
		"genres": ["movie-foreign"],
		"year": "2000"
	},
	{
		"id": 122,
		"name": "Шоу Трумана",
		"nameOrig": "The Truman Show",
		"genres": ["movie-foreign"],
		"year": "1998"
	},
	{
		"id": 123,
		"name": "Игры разума",
		"nameOrig": "A Beautiful Mind",
		"genres": ["movie-foreign"],
		"year": "2001"
	},
	{
		"id": 124,
		"name": "Джанго освобожденный",
		"nameOrig": "Django Unchained",
		"genres": ["movie-foreign"],
		"year": "2012"
	},
	{
		"id": 125,
		"name": "1408",
		"nameOrig": "1408",
		"genres": ["movie-foreign"],
		"year": "2007"
	},
	{
		"id": 126,
		"name": "Останься со мной",
		"nameOrig": "Stand by Me",
		"genres": ["movie-foreign"],
		"year": "1986"
	},
	{
		"id": 127,
		"name": "Перл-Харбор",
		"nameOrig": "Pearl Harbor",
		"genres": ["movie-foreign"],
		"year": "2001"
	},
	{
		"id": 128,
		"name": "Королевство полной луны",
		"nameOrig": "Moonrise Kingdom",
		"genres": ["movie-foreign"],
		"year": "2012"
	},
	{
		"id": 129,
		"name": "Властелин колец: Две крепости",
		"nameOrig": "The Lord of the Rings: The Two Towers",
		"genres": ["movie-foreign"],
		"year": "2002"
	},
	{
		"id": 130,
		"name": "Кадры",
		"nameOrig": "The Internship",
		"genres": ["movie-foreign"],
		"year": "2013"
	},
	{
		"id": 131,
		"name": "Сопрано",
		"nameOrig": "The Sopranos",
		"genres": ["series-foreign"],
		"year": "1999 - 2007"
	},
	{
		"id": 132,
		"name": "50 первых поцелуев",
		"nameOrig": "50 First Dates",
		"genres": ["movie-foreign"],
		"year": "2004"
	},
	{
		"id": 133,
		"name": "Управление гневом",
		"nameOrig": "Anger Management",
		"genres": ["movie-foreign"],
		"year": "2003"
	},
	{
		"id": 134,
		"name": "Стажёр",
		"nameOrig": "The Intern",
		"genres": ["movie-foreign"],
		"year": "2015"
	},
	{
		"id": 135,
		"name": "Дэдпул",
		"nameOrig": "Deadpool",
		"genres": ["movie-foreign"],
		"year": "2016"
	},
	{
		"id": 136,
		"name": "Загадочная история Бенджамина Баттона",
		"nameOrig": "The Curious Case of Benjamin Button",
		"genres": ["movie-foreign"],
		"year": "2008"
	},
	{
		"id": 137,
		"name": "Знакомьтесь, Джо Блэк",
		"nameOrig": "Meet Joe Black",
		"genres": ["movie-foreign"],
		"year": "1998"
	},
	{
		"id": 138,
		"name": "Нефть",
		"nameOrig": "There Will Be Blood",
		"genres": ["movie-foreign"],
		"year": "2007"
	},
	{
		"id": 139,
		"name": "Факультет",
		"nameOrig": "The Faculty",
		"genres": ["movie-foreign"],
		"year": "1998"
	},
	{
		"id": 140,
		"name": "Бойцовский клуб",
		"nameOrig": "Fight Club",
		"genres": ["movie-foreign"],
		"year": "1999"
	},
	{
		"id": 141,
		"name": "Области тьмы",
		"nameOrig": "Limitless",
		"genres": ["movie-foreign"],
		"year": "2011"
	},
	{
		"id": 142,
		"name": "После прочтения сжечь",
		"nameOrig": "Burn After Reading",
		"genres": ["movie-foreign"],
		"year": "2008"
	},
	{
		"id": 143,
		"name": "Телефонная будка",
		"nameOrig": "Phone Booth",
		"genres": ["movie-foreign"],
		"year": "2002"
	},
	{
		"id": 144,
		"name": "Двадцать одно",
		"nameOrig": "21",
		"genres": ["movie-foreign"],
		"year": "2008"
	},
	{
		"id": 145,
		"name": "Духless",
		"nameOrig": "Духless",
		"genres": ["movie-russian"],
		"year": "2011"
	},
	{
		"id": 146,
		"name": "Пять невест",
		"nameOrig": "Пять невест",
		"genres": ["movie-russian"],
		"year": "2011"
	},
	{
		"id": 147,
		"name": "О чём говорят мужчины",
		"nameOrig": "О чём говорят мужчины",
		"genres": ["movie-russian"],
		"year": "2010"
	},
	{
		"id": 148,
		"name": "Властелин колец: Возвращение короля",
		"nameOrig": "The Lord of the Rings: The Return of the King",
		"genres": ["movie-foreign"],
		"year": "2003"
	},
	{
		"id": 149,
		"name": "История игрушек",
		"nameOrig": "Toy Story",
		"genres": ["cartoon-foreign"],
		"year": "1995"
	},
	{
		"id": 150,
		"name": "Адреналин",
		"nameOrig": "Crank",
		"genres": ["movie-foreign"],
		"year": "2006"
	},
	{
		"id": 151,
		"name": "В погоне за счастьем",
		"nameOrig": "The Pursuit of Happyness",
		"genres": ["movie-foreign"],
		"year": "2006"
	},
	{
		"id": 152,
		"name": "Ярость",
		"nameOrig": "Fury",
		"genres": ["movie-foreign"],
		"year": "2014"
	},
	{
		"id": 153,
		"name": "Таксист",
		"nameOrig": "Taxi Driver",
		"genres": ["movie-foreign"],
		"year": "1976"
	},
	{
		"id": 154,
		"name": "Сияние",
		"nameOrig": "The Shining",
		"genres": ["movie-foreign"],
		"year": "1980"
	},
	{
		"id": 155,
		"name": "Знакомство с родителями",
		"nameOrig": "Meet the Parents",
		"genres": ["movie-foreign"],
		"year": "2000"
	},
	{
		"id": 156,
		"name": "Шрек",
		"nameOrig": "Shrek",
		"genres": ["cartoon-foreign"],
		"year": "2001"
	},
	{
		"id": 157,
		"name": "Законопослушный гражданин",
		"nameOrig": "Law Abiding Citizen",
		"genres": ["movie-foreign"],
		"year": "2009"
	},
	{
		"id": 158,
		"name": "Заводной апельсин",
		"nameOrig": "A Clockwork Orange",
		"genres": ["movie-foreign"],
		"year": "1971"
	},
	{
		"id": 159,
		"name": "…А в душе я танцую",
		"nameOrig": "Inside I'm Dancing",
		"genres": ["movie-foreign"],
		"year": "2004"
	},
	{
		"id": 160,
		"name": "Плезантвиль",
		"nameOrig": "Pleasantville",
		"genres": ["movie-foreign"],
		"year": "1998"
	},
	{
		"id": 161,
		"name": "Король Лев",
		"nameOrig": "The Lion King",
		"genres": ["cartoon-foreign"],
		"year": "1994"
	},
	{
		"id": 162,
		"name": "Всегда говори «ДА»",
		"nameOrig": "Yes Man",
		"genres": ["movie-foreign"],
		"year": "2008"
	},
	{
		"id": 163,
		"name": "Особо опасен",
		"nameOrig": "Wanted",
		"genres": ["movie-foreign"],
		"year": "2008"
	},
	{
		"id": 164,
		"name": "Назад в будущее",
		"nameOrig": "Back to the Future",
		"genres": ["movie-foreign"],
		"year": "1985"
	},
	{
		"id": 165,
		"name": "Пятый элемент",
		"nameOrig": "The Fifth Element",
		"genres": ["movie-foreign"],
		"year": "1997"
	},
	{
		"id": 166,
		"name": "Остров проклятых",
		"nameOrig": "Shutter Island",
		"genres": ["movie-foreign"],
		"year": "2009"
	},
	{
		"id": 167,
		"name": "Форсаж",
		"nameOrig": "The Fast and the Furious",
		"genres": ["movie-foreign"],
		"year": "2001"
	},
	{
		"id": 168,
		"name": "Маска",
		"nameOrig": "The Mask",
		"genres": ["movie-foreign"],
		"year": "1994"
	},
	{
		"id": 169,
		"name": "Социальная сеть",
		"nameOrig": "The Social Network",
		"genres": ["movie-foreign"],
		"year": "2010"
	},
	{
		"id": 170,
		"name": "Невидимая сторона",
		"nameOrig": "The Blind Side",
		"genres": ["movie-foreign"],
		"year": "2009"
	},
	{
		"id": 171,
		"name": "Шерлок",
		"nameOrig": "Sherlock",
		"genres": ["series-foreign"],
		"year": "2010 - 2017"
	},
	{
		"id": 172,
		"name": "Вечное сияние чистого разума",
		"nameOrig": "Eternal Sunshine of the Spotless Mind",
		"genres": ["movie-foreign"],
		"year": "2004"
	},
	{
		"id": 173,
		"name": "Американский психопат",
		"nameOrig": "American Psycho",
		"genres": ["movie-foreign"],
		"year": "2000"
	},
	{
		"id": 174,
		"name": "Волк с Уолл-стрит",
		"nameOrig": "The Wolf of Wall Street",
		"genres": ["movie-foreign"],
		"year": "2013"
	},
	{
		"id": 175,
		"name": "В поисках Дори",
		"nameOrig": "Finding Dory",
		"genres": ["cartoon-foreign"],
		"year": "2016"
	},
	{
		"id": 176,
		"name": "Неадекватные люди",
		"nameOrig": "Неадекватные люди",
		"genres": ["movie-russian"],
		"year": "2010"
	},
	{
		"id": 177,
		"name": "Географ глобус пропил",
		"nameOrig": "Географ глобус пропил",
		"genres": ["movie-russian"],
		"year": "2013"
	},
	{
		"id": 178,
		"name": "Идиократия",
		"nameOrig": "Idiocracy",
		"genres": ["movie-foreign"],
		"year": "2005"
	},
	{
		"id": 179,
		"name": "Гадкий я",
		"nameOrig": "Despicable Me",
		"genres": ["cartoon-foreign"],
		"year": "2010"
	},
	{
		"id": 180,
		"name": "Рапунцель: Запутанная история",
		"nameOrig": "Tangled",
		"genres": ["cartoon-foreign"],
		"year": "2010"
	},
	{
		"id": 181,
		"name": "Джентльмены удачи",
		"nameOrig": "Джентльмены удачи",
		"genres": ["movie-soviet"],
		"year": "1971"
	},
	{
		"id": 182,
		"name": "Душа",
		"nameOrig": "Soul",
		"genres": ["cartoon-foreign"],
		"year": "2020"
	},
	{
		"id": 183,
		"name": "Иван Васильевич меняет профессию",
		"nameOrig": "Иван Васильевич меняет профессию",
		"genres": ["movie-soviet"],
		"year": "1973"
	},
	{
		"id": 184,
		"name": "Я, робот",
		"nameOrig": "I, Robot",
		"genres": ["movie-foreign"],
		"year": "2004"
	},
	{
		"id": 185,
		"name": "Трансформеры",
		"nameOrig": "Transformers",
		"genres": ["movie-foreign"],
		"year": "2007"
	},
	{
		"id": 186,
		"name": "Однажды в… Голливуде",
		"nameOrig": "Once Upon a Time in... Hollywood",
		"genres": ["movie-foreign"],
		"year": "2019"
	},
	{
		"id": 187,
		"name": "Разрушение",
		"nameOrig": "Demolition",
		"genres": ["movie-foreign"],
		"year": "2015"
	},
	{
		"id": 188,
		"name": "Инопланетянин",
		"nameOrig": "E.T. the Extra-Terrestrial",
		"genres": ["movie-foreign"],
		"year": "1982"
	},
	{
		"id": 189,
		"name": "Унесённые призраками",
		"nameOrig": "Sen to Chihiro no kamikakushi",
		"genres": ["cartoon-foreign"],
		"year": "2001"
	},
	{
		"id": 190,
		"name": "Угнать за 60 секунд",
		"nameOrig": "Gone in Sixty Seconds",
		"genres": ["movie-foreign"],
		"year": "2000"
	},
	{
		"id": 191,
		"name": "Капитан Фантастик",
		"nameOrig": "Captain Fantastic",
		"genres": ["movie-foreign"],
		"year": "2016"
	},
	{
		"id": 192,
		"name": "Пароль «Рыба-меч»",
		"nameOrig": "Swordfish",
		"genres": ["movie-foreign"],
		"year": "2001"
	},
	{
		"id": 193,
		"name": "Милые кости",
		"nameOrig": "The Lovely Bones",
		"genres": ["movie-foreign"],
		"year": "2009"
	},
	{
		"id": 194,
		"name": "Один дома 2: Затерянный в Нью-Йорке",
		"nameOrig": "Home Alone 2: Lost in New York",
		"genres": ["movie-foreign"],
		"year": "1992"
	},
	{
		"id": 195,
		"name": "Аритмия",
		"nameOrig": "Аритмия",
		"genres": ["movie-russian"],
		"year": "2017"
	},
	{
		"id": 196,
		"name": "Без границ",
		"nameOrig": "Без границ",
		"genres": ["movie-russian"],
		"year": "2015"
	},
	{
		"id": 197,
		"name": "Подарок на рождество",
		"nameOrig": "Jingle All the Way",
		"genres": ["movie-foreign"],
		"year": "1996"
	},
	{
		"id": 198,
		"name": "Лёд",
		"nameOrig": "Лёд",
		"genres": ["movie-russian"],
		"year": "2018"
	},
	{
		"id": 199,
		"name": "Гуляй, Вася!",
		"nameOrig": "Гуляй, Вася!",
		"genres": ["movie-russian"],
		"year": "2016"
	},
	{
		"id": 200,
		"name": "Скотт Пилигрим против всех",
		"nameOrig": "Scott Pilgrim vs. the World",
		"genres": ["movie-foreign"],
		"year": "2010"
	},
	{
		"id": 201,
		"name": "Холоп",
		"nameOrig": "Холоп",
		"genres": ["movie-russian"],
		"year": "2019"
	},
	{
		"id": 202,
		"name": "300 спартанцев",
		"nameOrig": "300",
		"genres": ["movie-foreign"],
		"year": "2007"
	},
	{
		"id": 203,
		"name": "Артист",
		"nameOrig": "The Artist",
		"genres": ["movie-foreign"],
		"year": "2011"
	},
	{
		"id": 204,
		"name": "Легенда №17",
		"nameOrig": "Легенда №17",
		"genres": ["movie-russian"],
		"year": "2012"
	},
	{
		"id": 205,
		"name": "Железная хватка",
		"nameOrig": "True Grit",
		"genres": ["movie-foreign"],
		"year": "2010"
	},
	{
		"id": 206,
		"name": "Большой куш",
		"nameOrig": "Snatch",
		"genres": ["movie-foreign"],
		"year": "2000"
	},
	{
		"id": 207,
		"name": "Прочь",
		"nameOrig": "Get Out",
		"genres": ["movie-foreign"],
		"year": "2017"
	},
	{
		"id": 208,
		"name": "Брат",
		"nameOrig": "Брат",
		"genres": ["movie-russian"],
		"year": "1997"
	},
	{
		"id": 209,
		"name": "Человек-паук 2",
		"nameOrig": "Spider-Man 2",
		"genres": ["movie-foreign"],
		"year": "2004"
	},
	{
		"id": 210,
		"name": "Форрест Гамп",
		"nameOrig": "Forrest Gump",
		"genres": ["movie-foreign"],
		"year": "1994"
	},
	{
		"id": 211,
		"name": "Автостопом по галактике",
		"nameOrig": "The Hitchhiker's Guide to the Galaxy",
		"genres": ["movie-foreign"],
		"year": "2005"
	},
	{
		"id": 212,
		"name": "Люди Икс",
		"nameOrig": "X-Men",
		"genres": ["movie-foreign"],
		"year": "2000"
	},
	{
		"id": 213,
		"name": "Люди Икс 2",
		"nameOrig": "X-Men 2",
		"genres": ["movie-foreign"],
		"year": "2003"
	},
	{
		"id": 214,
		"name": "Три билборда на границе Эббинга, Миссури",
		"nameOrig": "Three Billboards Outside Ebbing, Missouri",
		"genres": ["movie-foreign"],
		"year": "2017"
	},
	{
		"id": 215,
		"name": "Старикам тут не место",
		"nameOrig": "No Country for Old Men",
		"genres": ["movie-foreign"],
		"year": "2007"
	},
	{
		"id": 216,
		"name": "Сорвиголова",
		"nameOrig": "Daredevil",
		"genres": ["movie-foreign"],
		"year": "2003"
	},
	{
		"id": 217,
		"name": "Назад в будущее 2",
		"nameOrig": "Back to the Future Part II",
		"genres": ["movie-foreign"],
		"year": "1989"
	},
	{
		"id": 218,
		"name": "Назад в будущее 3",
		"nameOrig": "Back to the Future Part III",
		"genres": ["movie-foreign"],
		"year": "1990"
	},
	{
		"id": 219,
		"name": "Семь",
		"nameOrig": "Seven",
		"genres": ["movie-foreign"],
		"year": "1995"
	},
	{
		"id": 220,
		"name": "Марсианин",
		"nameOrig": "The Martian",
		"genres": ["movie-foreign"],
		"year": "2015"
	},
	{
		"id": 221,
		"name": "Интервью с вампиром",
		"nameOrig": "Interview with the Vampire: The Vampire Chronicles",
		"genres": ["movie-foreign"],
		"year": "1994"
	},
	{
		"id": 222,
		"name": "Гладиатор",
		"nameOrig": "Gladiator",
		"genres": ["movie-foreign"],
		"year": "2000"
	},
	{
		"id": 223,
		"name": "Грязь",
		"nameOrig": "Filth",
		"genres": ["movie-foreign"],
		"year": "2013"
	},
	{
		"id": 224,
		"name": "Малыш на драйве",
		"nameOrig": "Baby Driver",
		"genres": ["movie-foreign"],
		"year": "2017"
	},
	{
		"id": 225,
		"name": "Три плюс два",
		"nameOrig": "Три плюс два",
		"genres": ["movie-soviet"],
		"year": "1963"
	},
	{
		"id": 226,
		"name": "По соображениям совести",
		"nameOrig": "Hacksaw Ridge",
		"genres": ["movie-foreign"],
		"year": "2016"
	},
	{
		"id": 227,
		"name": "Холодное сердце",
		"nameOrig": "Frozen",
		"genres": ["cartoon-foreign"],
		"year": "2013"
	},
	{
		"id": 228,
		"name": "Кролик Джоджо",
		"nameOrig": "Jojo Rabbit",
		"genres": ["movie-foreign"],
		"year": "2019"
	},
	{
		"id": 229,
		"name": "Хищник",
		"nameOrig": "Predator",
		"genres": ["movie-foreign"],
		"year": "1987"
	},
	{
		"id": 230,
		"name": "Мементо",
		"nameOrig": "Memento",
		"genres": ["movie-foreign"],
		"year": "2000"
	},
	{
		"id": 231,
		"name": "Господин Никто",
		"nameOrig": "Mr. Nobody",
		"genres": ["movie-foreign"],
		"year": "2009"
	},
	{
		"id": 232,
		"name": "Правдивая ложь",
		"nameOrig": "True Lies",
		"genres": ["movie-foreign"],
		"year": "1994"
	},
	{
		"id": 233,
		"name": "Район №9",
		"nameOrig": "District 9",
		"genres": ["movie-foreign"],
		"year": "2009"
	},
	{
		"id": 234,
		"name": "Робот по имени Чаппи",
		"nameOrig": "Chappie",
		"genres": ["movie-foreign"],
		"year": "2015"
	},
	{
		"id": 235,
		"name": "Живая сталь",
		"nameOrig": "Real Steel",
		"genres": ["movie-foreign"],
		"year": "2011"
	},
	{
		"id": 236,
		"name": "Крупная рыба",
		"nameOrig": "Big Fish",
		"genres": ["movie-foreign"],
		"year": "2003"
	},
	{
		"id": 237,
		"name": "Главный герой",
		"nameOrig": "Free Guy",
		"genres": ["movie-foreign"],
		"year": "2021"
	},
	{
		"id": 238,
		"name": "Город грехов",
		"nameOrig": "Sin City",
		"genres": ["movie-foreign"],
		"year": "2005"
	},
	{
		"id": 239,
		"name": "Бешеные псы",
		"nameOrig": "Reservoir Dogs",
		"genres": ["movie-foreign"],
		"year": "1991"
	},
	{
		"id": 240,
		"name": "Римские приключения",
		"nameOrig": "To Rome with Love",
		"genres": ["movie-foreign"],
		"year": "2012"
	},
	{
		"id": 241,
		"name": "Безумный Макс: Дорога ярости",
		"nameOrig": "Mad Max: Fury Road",
		"genres": ["movie-foreign"],
		"year": "2015"
	},
	{
		"id": 242,
		"name": "Исходный код",
		"nameOrig": "Source Code",
		"genres": ["movie-foreign"],
		"year": "2011"
	},
	{
		"id": 243,
		"name": "Воины",
		"nameOrig": "The Warriors",
		"genres": ["movie-foreign"],
		"year": "1979"
	},
	{
		"id": 244,
		"name": "Тачки",
		"nameOrig": "Cars",
		"genres": ["cartoon-foreign"],
		"year": "2006"
	},
	{
		"id": 245,
		"name": "500 дней лета",
		"nameOrig": "(500) Days of Summer",
		"genres": ["movie-foreign"],
		"year": "2009"
	},
	{
		"id": 246,
		"name": "Миллионер из трущоб",
		"nameOrig": "Slumdog Millionaire",
		"genres": ["movie-foreign"],
		"year": "2008"
	},
	{
		"id": 247,
		"name": "Еще по одной",
		"nameOrig": "Druk",
		"genres": ["movie-foreign"],
		"year": "2020"
	},
	{
		"id": 248,
		"name": "Кунг-фу Панда",
		"nameOrig": "Kung Fu Panda",
		"genres": ["cartoon-foreign"],
		"year": "2008"
	},
	{
		"id": 249,
		"name": "Майор",
		"nameOrig": "Майор",
		"genres": ["movie-russian"],
		"year": "2013"
	},
	{
		"id": 250,
		"name": "Каратэ-пацан",
		"nameOrig": "The Karate Kid",
		"genres": ["movie-foreign"],
		"year": "2010"
	},
	{
		"id": 251,
		"name": "Черная дыра",
		"nameOrig": "Pitch Black",
		"genres": ["movie-foreign"],
		"year": "1999"
	},
	{
		"id": 252,
		"name": "Вечерний экспресс «Сансет Лимитед»",
		"nameOrig": "The Sunset Limited",
		"genres": ["movie-foreign"],
		"year": "2011"
	},
	{
		"id": 253,
		"name": "Американская история X",
		"nameOrig": "American History X",
		"genres": ["movie-foreign"],
		"year": "1998"
	},
	{
		"id": 254,
		"name": "Криминальное чтиво",
		"nameOrig": "Pulp Fiction",
		"genres": ["movie-foreign"],
		"year": "1994"
	},
	{
		"id": 255,
		"name": "Трансформеры 3: Тёмная сторона Луны",
		"nameOrig": "Transformers: Dark of the Moon",
		"genres": ["movie-foreign"],
		"year": "2011"
	},
	{
		"id": 256,
		"name": "Вокруг света за 80 дней",
		"nameOrig": "Around the World in 80 Days",
		"genres": ["movie-foreign"],
		"year": "2004"
	},
	{
		"id": 257,
		"name": "Стиляги",
		"nameOrig": "Стиляги",
		"genres": ["movie-russian"],
		"year": "2008"
	},
	{
		"id": 258,
		"name": "Страна садов",
		"nameOrig": "Garden State",
		"genres": ["movie-foreign"],
		"year": "2003"
	},
	{
		"id": 259,
		"name": "Евротур",
		"nameOrig": "EuroTrip",
		"genres": ["movie-foreign"],
		"year": "2004"
	},
	{
		"id": 260,
		"name": "Семьянин",
		"nameOrig": "The Family Man",
		"genres": ["movie-foreign"],
		"year": "2000"
	},
	{
		"id": 261,
		"name": "Дьявол в деталях",
		"nameOrig": "The Little Things",
		"genres": ["movie-foreign"],
		"year": "2020"
	},
	{
		"id": 262,
		"name": "Мегамозг",
		"nameOrig": "Megamind",
		"genres": ["cartoon-foreign"],
		"year": "2010"
	},
	{
		"id": 263,
		"name": "Мой парень — псих",
		"nameOrig": "Silver Linings Playbook",
		"genres": ["movie-foreign"],
		"year": "2012"
	},
	{
		"id": 264,
		"name": "Мальчишник в Вегасе",
		"nameOrig": "The Hangover",
		"genres": ["movie-foreign"],
		"year": "2009"
	},
	{
		"id": 265,
		"name": "Омерзительная восьмерка",
		"nameOrig": "The Hateful Eight",
		"genres": ["movie-foreign"],
		"year": "2015"
	},
	{
		"id": 266,
		"name": "Каникулы строгого режима",
		"nameOrig": "Каникулы строгого режима",
		"genres": ["movie-russian"],
		"year": "2009"
	},
	{
		"id": 267,
		"name": "Невероятная жизнь Уолтера Митти",
		"nameOrig": "The Secret Life of Walter Mitty",
		"genres": ["movie-foreign"],
		"year": "2013"
	},
	{
		"id": 268,
		"name": "Настоящая любовь",
		"nameOrig": "True Romance",
		"genres": ["movie-foreign"],
		"year": "1993"
	},
	{
		"id": 269,
		"name": "Место под соснами",
		"nameOrig": "The Place Beyond the Pines",
		"genres": ["movie-foreign"],
		"year": "2012"
	},
	{
		"id": 270,
		"name": "Эластико",
		"nameOrig": "Эластико",
		"genres": ["movie-russian"],
		"year": "2016"
	},
	{
		"id": 271,
		"name": "Брюс Всемогущий",
		"nameOrig": "Bruce Almighty",
		"genres": ["movie-foreign"],
		"year": "2003"
	},
	{
		"id": 272,
		"name": "Хэнкок",
		"nameOrig": "Hancock",
		"genres": ["movie-foreign"],
		"year": "2008"
	},
	{
		"id": 273,
		"name": "Что гложет Гилберта Грейпа?",
		"nameOrig": "What's Eating Gilbert Grape",
		"genres": ["movie-foreign"],
		"year": "1993"
	},
	{
		"id": 274,
		"name": "Операция «Арго»",
		"nameOrig": "Argo",
		"genres": ["movie-foreign"],
		"year": "2012"
	},
	{
		"id": 275,
		"name": "Исчезнувшая",
		"nameOrig": "Gone Girl",
		"genres": ["movie-foreign"],
		"year": "2014"
	},
	{
		"id": 276,
		"name": "Зависнуть в Палм-Спрингс",
		"nameOrig": "Palm Springs",
		"genres": ["movie-foreign"],
		"year": "2020"
	},
	{
		"id": 277,
		"name": "Третий лишний",
		"nameOrig": "Ted",
		"genres": ["movie-foreign"],
		"year": "2012"
	},
	{
		"id": 278,
		"name": "Король говорит!",
		"nameOrig": "The King's Speech",
		"genres": ["movie-foreign"],
		"year": "2010"
	},
	{
		"id": 279,
		"name": "Ирония судьбы, или С легким паром!",
		"nameOrig": "Ирония судьбы, или С легким паром!",
		"genres": ["movie-soviet"],
		"year": "1975"
	},
	{
		"id": 280,
		"name": "Громкая связь",
		"nameOrig": "Громкая связь",
		"genres": ["movie-russian"],
		"year": "2018"
	},
	{
		"id": 281,
		"name": "Вольт",
		"nameOrig": "Bolt",
		"genres": ["cartoon-foreign"],
		"year": "2008"
	},
	{
		"id": 282,
		"name": "Семейка Крудс",
		"nameOrig": "The Croods",
		"genres": ["cartoon-foreign"],
		"year": "2013"
	},
	{
		"id": 283,
		"name": "Тайная жизнь домашних животных",
		"nameOrig": "The Secret Life of Pets",
		"genres": ["cartoon-foreign"],
		"year": "2016"
	},
	{
		"id": 284,
		"name": "Люпен",
		"nameOrig": "Lupin",
		"genres": ["series-foreign"],
		"year": "2021"
	},
	{
		"id": 285,
		"name": "Утреннее шоу",
		"nameOrig": "The Morning Show",
		"genres": ["series-foreign"],
		"year": "2019"
	},
	{
		"id": 286,
		"name": "Сыны анархии",
		"nameOrig": "Sons of Anarchy",
		"genres": ["series-foreign"],
		"year": "2008 - 2014"
	},
	{
		"id": 287,
		"name": "Ведьмак",
		"nameOrig": "The Witcher",
		"genres": ["series-foreign"],
		"year": "2019"
	},
	{
		"id": 288,
		"name": "Чернобыль",
		"nameOrig": "Chernobyl",
		"genres": ["series-foreign"],
		"year": "2019"
	},
	{
		"id": 289,
		"name": "Остаться в живых",
		"nameOrig": "Lost",
		"genres": ["series-foreign"],
		"year": "2004 - 2010"
	},
	{
		"id": 290,
		"name": "Побег",
		"nameOrig": "Prison Break",
		"genres": ["series-foreign"],
		"year": "2005 - 2017"
	},
	{
		"id": 291,
		"name": "РЭД",
		"nameOrig": "RED",
		"genres": ["movie-foreign"],
		"year": "2010"
	},
	{
		"id": 292,
		"name": "Шрек 2",
		"nameOrig": "Shrek 2",
		"genres": ["cartoon-foreign"],
		"year": "2004"
	},
	{
		"id": 293,
		"name": "Шрек Третий",
		"nameOrig": "Shrek the Third",
		"genres": ["cartoon-foreign"],
		"year": "2007"
	},
	{
		"id": 294,
		"name": "Шерлок Холмс",
		"nameOrig": "Sherlock Holmes",
		"genres": ["movie-foreign"],
		"year": "2009"
	},
	{
		"id": 295,
		"name": "Бронсон",
		"nameOrig": "Bronson",
		"genres": ["movie-foreign"],
		"year": "2008"
	},
	{
		"id": 296,
		"name": "Моя левая нога",
		"nameOrig": "My Left Foot: The Story of Christy Brown",
		"genres": ["movie-foreign"],
		"year": "1989"
	},
	{
		"id": 297,
		"name": "Сказка о потерянном времени",
		"nameOrig": "Сказка о потерянном времени",
		"genres": ["movie-soviet"],
		"year": "1964"
	},
	{
		"id": 298,
		"name": "Вовка в тридевятом царстве",
		"nameOrig": "Вовка в тридевятом царстве",
		"genres": ["cartoon-soviet"],
		"year": "1965"
	},
	{
		"id": 299,
		"name": "Цветик-семицветик",
		"nameOrig": "Цветик-семицветик",
		"genres": ["cartoon-soviet"],
		"year": "1948"
	},
	{
		"id": 300,
		"name": "Следствие ведут Колобки",
		"nameOrig": "Следствие ведут Колобки",
		"genres": ["cartoon-soviet"],
		"year": "1986"
	},
	{
		"id": 301,
		"name": "Золотая антилопа",
		"nameOrig": "Золотая антилопа",
		"genres": ["cartoon-soviet"],
		"year": "1954"
	},
	{
		"id": 302,
		"name": "Сваты",
		"nameOrig": "Сваты",
		"genres": ["series-russian"],
		"year": "2008 - 2021"
	},
	{
		"id": 303,
		"name": "Папины дочки",
		"nameOrig": "Папины дочки",
		"genres": ["series-russian"],
		"year": "2007 - 2013"
	},
	{
		"id": 304,
		"name": "Кухня",
		"nameOrig": "Кухня",
		"genres": ["series-russian"],
		"year": "2012 - 2016"
	},
	{
		"id": 305,
		"name": "Универ",
		"nameOrig": "Универ",
		"genres": ["series-russian"],
		"year": "2008 - 2011"
	},
	{
		"id": 306,
		"name": "Воронины",
		"nameOrig": "Воронины",
		"genres": ["series-russian"],
		"year": "2009 - 2019"
	},
	{
		"id": 307,
		"name": "Миссия: невыполнима",
		"nameOrig": "Mission: Impossible",
		"genres": ["movie-foreign"],
		"year": "1996"
	},
	{
		"id": 308,
		"name": "Миссия: невыполнима 2",
		"nameOrig": "Mission: Impossible II",
		"genres": ["movie-foreign"],
		"year": "2000"
	},
	{
		"id": 309,
		"name": "Терминал",
		"nameOrig": "The Terminal",
		"genres": ["movie-foreign"],
		"year": "2004"
	},
	{
		"id": 310,
		"name": "Эдди «Орёл»",
		"nameOrig": "Eddie the Eagle",
		"genres": ["movie-foreign"],
		"year": "2015"
	},
	{
		"id": 311,
		"name": "Резня",
		"nameOrig": "Carnage",
		"genres": ["movie-foreign"],
		"year": "2011"
	},
	{
		"id": 312,
		"name": "Армагеддон",
		"nameOrig": "Armageddon",
		"genres": ["movie-foreign"],
		"year": "1998"
	},
	{
		"id": 313,
		"name": "Зловещие мертвецы",
		"nameOrig": "The Evil Dead",
		"genres": ["movie-foreign"],
		"year": "1981"
	},
	{
		"id": 314,
		"name": "Довод",
		"nameOrig": "Tenet",
		"genres": ["movie-foreign"],
		"year": "2020"
	},
	{
		"id": 315,
		"name": "Пипец",
		"nameOrig": "Kick-Ass",
		"genres": ["movie-foreign"],
		"year": "2010"
	},
	{
		"id": 316,
		"name": "Молчание ягнят",
		"nameOrig": "The Silence of the Lambs",
		"genres": ["movie-foreign"],
		"year": "1990"
	},
	{
		"id": 317,
		"name": "Мексиканец",
		"nameOrig": "The Mexican",
		"genres": ["movie-foreign"],
		"year": "2001"
	},
	{
		"id": 318,
		"name": "Мистер Робот",
		"nameOrig": "Mr. Robot",
		"genres": ["series-foreign"],
		"year": "2015 - 2019"
	},
	{
		"id": 319,
		"name": "Турист",
		"nameOrig": "The Tourist",
		"genres": ["movie-foreign"],
		"year": "2010"
	},
	{
		"id": 320,
		"name": "Без чувств",
		"nameOrig": "Senseless",
		"genres": ["movie-foreign"],
		"year": "1998"
	},
	{
		"id": 321,
		"name": "Бегущий в лабиринте",
		"nameOrig": "The Maze Runner",
		"genres": ["movie-foreign"],
		"year": "2014"
	},
	{
		"id": 322,
		"name": "Тупой и еще тупее",
		"nameOrig": "Dumb and Dumber",
		"genres": ["movie-foreign"],
		"year": "1994"
	},
	{
		"id": 323,
		"name": "Хотел бы я быть здесь",
		"nameOrig": "Wish I Was Here",
		"genres": ["movie-foreign"],
		"year": "2014"
	},
	{
		"id": 324,
		"name": "Телохранитель киллера",
		"nameOrig": "The Hitman's Bodyguard",
		"genres": ["movie-foreign"],
		"year": "2017"
	},
	{
		"id": 325,
		"name": "Игры джентельменов",
		"nameOrig": "The Ladykillers",
		"genres": ["movie-foreign"],
		"year": "2004"
	},
	{
		"id": 326,
		"name": "Всё или ничего",
		"nameOrig": "The Longest Yard",
		"genres": ["movie-foreign"],
		"year": "2005"
	},
	{
		"id": 327,
		"name": "Хоббит: Нежданное путешествие",
		"nameOrig": "The Hobbit: An Unexpected Journey",
		"genres": ["movie-foreign"],
		"year": "2012"
	},
	{
		"id": 328,
		"name": "Хоббит: Пустошь Смауга",
		"nameOrig": "The Hobbit: An Unexpected Journey",
		"genres": ["movie-foreign"],
		"year": "2013"
	},
	{
		"id": 329,
		"name": "Хоббит: Битва пяти воинств",
		"nameOrig": "The Hobbit: The Battle of the Five Armies",
		"genres": ["movie-foreign"],
		"year": "2014"
	},
	{
		"id": 330,
		"name": "Больше, чем любовь",
		"nameOrig": "A Lot Like Love",
		"genres": ["movie-foreign"],
		"year": "2005"
	},
	{
		"id": 331,
		"name": "Грань будущего",
		"nameOrig": "Edge of Tomorrow",
		"genres": ["movie-foreign"],
		"year": "2014"
	},
	{
		"id": 332,
		"name": "Эволюция",
		"nameOrig": "Evolution",
		"genres": ["movie-foreign"],
		"year": "2001"
	},
	{
		"id": 333,
		"name": "Паранорман, или Как приручить зомби",
		"nameOrig": "ParaNorman",
		"genres": ["cartoon-foreign"],
		"year": "2012"
	},
	{
		"id": 334,
		"name": "Мне бы в небо",
		"nameOrig": "Up in the Air",
		"genres": ["movie-foreign"],
		"year": "2009"
	},
	{
		"id": 335,
		"name": "С меня хватит!",
		"nameOrig": "Falling Down",
		"genres": ["movie-foreign"],
		"year": "1992"
	},
	{
		"id": 336,
		"name": "Неистовый",
		"nameOrig": "Unhinged",
		"genres": ["movie-foreign"],
		"year": "2020"
	},
	{
		"id": 337,
		"name": "Эйс Вентура: Розыск домашних животных",
		"nameOrig": "Ace Ventura: Pet Detective",
		"genres": ["movie-foreign"],
		"year": "1993"
	},
	{
		"id": 338,
		"name": "Солдаты неудачи",
		"nameOrig": "Tropic Thunder",
		"genres": ["movie-foreign"],
		"year": "2008"
	},
	{
		"id": 339,
		"name": "Банды Нью-Йорка",
		"nameOrig": "Gangs of New York",
		"genres": ["movie-foreign"],
		"year": "2002"
	},
	{
		"id": 340,
		"name": "Охотники за привидениями",
		"nameOrig": "Ghostbusters",
		"genres": ["movie-foreign"],
		"year": "1984"
	},
	{
		"id": 341,
		"name": "Логан",
		"nameOrig": "Logan",
		"genres": ["movie-foreign"],
		"year": "2017"
	},
	{
		"id": 342,
		"name": "Гремлины",
		"nameOrig": "Gremlins",
		"genres": ["movie-foreign"],
		"year": "1984"
	},
	{
		"id": 343,
		"name": "Дорогая, я уменьшил детей",
		"nameOrig": "Honey, I Shrunk the Kids",
		"genres": ["movie-foreign"],
		"year": "1989"
	},
	{
		"id": 344,
		"name": "Один день",
		"nameOrig": "One Day",
		"genres": ["movie-foreign"],
		"year": "2011"
	},
	{
		"id": 345,
		"name": "Тик-так... БУМ!",
		"nameOrig": "tick, tick...BOOM!",
		"genres": ["movie-foreign"],
		"year": "2021"
	},
	{
		"id": 346,
		"name": "Скрытые фигуры",
		"nameOrig": "Hidden Figures",
		"genres": ["movie-foreign"],
		"year": "2016"
	},
	{
		"id": 347,
		"name": "Машина времени в джакузи",
		"nameOrig": "Hot Tub Time Machine",
		"genres": ["movie-foreign"],
		"year": "2010"
	},
	{
		"id": 348,
		"name": "На игле",
		"nameOrig": "Trainspotting",
		"genres": ["movie-foreign"],
		"year": "1995"
	},
	{
		"id": 349,
		"name": "Город героев",
		"nameOrig": "Big Hero 6",
		"genres": ["cartoon-foreign"],
		"year": "2014"
	},
	{
		"id": 350,
		"name": "Ральф",
		"nameOrig": "Wreck-It Ralph",
		"genres": ["cartoon-foreign"],
		"year": "2012"
	},
	{
		"id": 351,
		"name": "2012",
		"nameOrig": "2012",
		"genres": ["movie-foreign"],
		"year": "2009"
	},
	{
		"id": 352,
		"name": "Водная жизнь",
		"nameOrig": "The Life Aquatic with Steve Zissou",
		"genres": ["movie-foreign"],
		"year": "2004"
	},
	{
		"id": 353,
		"name": "Животное",
		"nameOrig": "The Animal",
		"genres": ["movie-foreign"],
		"year": "2001"
	},
	{
		"id": 354,
		"name": "День сурка",
		"nameOrig": "Groundhog Day",
		"genres": ["movie-foreign"],
		"year": "1993"
	},
	{
		"id": 355,
		"name": "Восьмидесятые",
		"nameOrig": "Восьмидесятые",
		"genres": ["series-russian"],
		"year": "2011 - 2016"
	},
	{
		"id": 356,
		"name": "Мы — Миллеры",
		"nameOrig": "We're the Millers",
		"genres": ["movie-foreign"],
		"year": "2013"
	},
	{
		"id": 357,
		"name": "Лицо со шрамом",
		"nameOrig": "Scarface",
		"genres": ["movie-foreign"],
		"year": "1983"
	},
	{
		"id": 358,
		"name": "Дюплекс",
		"nameOrig": "Duplex",
		"genres": ["movie-foreign"],
		"year": "2003"
	},
	{
		"id": 359,
		"name": "Убить Билла",
		"nameOrig": "Kill Bill: Vol. 1",
		"genres": ["movie-foreign"],
		"year": "2003"
	},
	{
		"id": 360,
		"name": "Гарри Поттер и философский камень",
		"nameOrig": "Harry Potter and the Sorcerer's Stone",
		"genres": ["movie-foreign"],
		"year": "2001"
	},
	{
		"id": 361,
		"name": "Гарри Поттер и Кубок огня",
		"nameOrig": "Harry Potter and the Goblet of Fire",
		"genres": ["movie-foreign"],
		"year": "2005"
	},
	{
		"id": 362,
		"name": "Побег из Шоушенка",
		"nameOrig": "The Shawshank Redemption",
		"genres": ["movie-foreign"],
		"year": "1994"
	},
	{
		"id": 363,
		"name": "Мертвец",
		"nameOrig": "Dead Man",
		"genres": ["movie-foreign"],
		"year": "1995"
	},
	{
		"id": 364,
		"name": "Последний киногерой",
		"nameOrig": "Last Action Hero",
		"genres": ["movie-foreign"],
		"year": "1993"
	},
	{
		"id": 365,
		"name": "Звонок",
		"nameOrig": "The Ring",
		"genres": ["movie-foreign"],
		"year": "2002"
	},
	{
		"id": 366,
		"name": "Рокки",
		"nameOrig": "Rocky",
		"genres": ["movie-foreign"],
		"year": "1976"
	},
	{
		"id": 367,
		"name": "25-й час",
		"nameOrig": "25th Hour",
		"genres": ["movie-foreign"],
		"year": "2002"
	},
	{
		"id": 368,
		"name": "Бумер",
		"nameOrig": "Бумер",
		"genres": ["movie-russian"],
		"year": "2003"
	},
	{
		"id": 369,
		"name": "Возвращение",
		"nameOrig": "Возвращение",
		"genres": ["movie-russian"],
		"year": "2003"
	},
	{
		"id": 370,
		"name": "Притяжение",
		"nameOrig": "Притяжение",
		"genres": ["movie-russian"],
		"year": "2017"
	},
	{
		"id": 371,
		"name": "Люблю тебя, чувак",
		"nameOrig": "I Love You, Man",
		"genres": ["movie-foreign"],
		"year": "2008"
	},
	{
		"id": 372,
		"name": "Ничего не вижу, ничего не слышу",
		"nameOrig": "See No Evil, Hear No Evil",
		"genres": ["movie-foreign"],
		"year": "1989"
	},
	{
		"id": 373,
		"name": "Хорошо быть тихоней",
		"nameOrig": "The Perks of Being a Wallflower",
		"genres": ["movie-foreign"],
		"year": "2012"
	},
	{
		"id": 374,
		"name": "Сверхъестественное",
		"nameOrig": "Supernatural",
		"genres": ["series-foreign"],
		"year": "2005 - 2020"
	},
	{
		"id": 375,
		"name": "Человек-муравей",
		"nameOrig": "Ant-Man",
		"genres": ["movie-foreign"],
		"year": "2015"
	},
	{
		"id": 376,
		"name": "8 миля",
		"nameOrig": "8 Mile",
		"genres": ["movie-foreign"],
		"year": "2002"
	},
	{
		"id": 377,
		"name": "Пролетая над гнездом кукушки",
		"nameOrig": "One Flew Over the Cuckoo's Nest",
		"genres": ["movie-foreign"],
		"year": "1975"
	},
	{
		"id": 378,
		"name": "Гарри Поттер и Принц-полукровка",
		"nameOrig": "Harry Potter and the Half-Blood Prince",
		"genres": ["movie-foreign"],
		"year": "2009"
	},
	{
		"id": 379,
		"name": "Пробуждение",
		"nameOrig": "Awakenings",
		"genres": ["movie-foreign"],
		"year": "1990"
	},
	{
		"id": 380,
		"name": "Начало",
		"nameOrig": "Inception",
		"genres": ["movie-foreign"],
		"year": "2010"
	},
	{
		"id": 381,
		"name": "Парк Юрского периода",
		"nameOrig": "Jurassic Park",
		"genres": ["movie-foreign"],
		"year": "1993"
	},
	{
		"id": 382,
		"name": "Заплати другому",
		"nameOrig": "Pay It Forward",
		"genres": ["movie-foreign"],
		"year": "2000"
	},
	{
		"id": 383,
		"name": "127 часов",
		"nameOrig": "127 Hours",
		"genres": ["movie-foreign"],
		"year": "2010"
	},
	{
		"id": 384,
		"name": "Мамы",
		"nameOrig": "Мамы",
		"genres": ["movie-russian"],
		"year": "2012"
	},
	{
		"id": 385,
		"name": "Белое солнце пустыни",
		"nameOrig": "Белое солнце пустыни",
		"genres": ["movie-soviet"],
		"year": "1969"
	},
	{
		"id": 386,
		"name": "Кин-дза-дза!",
		"nameOrig": "Кин-дза-дза!",
		"genres": ["movie-soviet"],
		"year": "1986"
	},
	{
		"id": 387,
		"name": "Гарри Поттер и Орден Феникса",
		"nameOrig": "Harry Potter and the Order of the Phoenix",
		"genres": ["movie-foreign"],
		"year": "2007"
	},
	{
		"id": 388,
		"name": "Малыш и Карлсон",
		"nameOrig": "Малыш и Карлсон",
		"genres": ["cartoon-soviet"],
		"year": "1968"
	},
	{
		"id": 389,
		"name": "Кто я?",
		"nameOrig": "Ngo si seoi",
		"genres": ["movie-foreign"],
		"year": "1998"
	},
	{
		"id": 390,
		"name": "Вечера на хуторе близ Диканьки",
		"nameOrig": "Вечера на хуторе близ Диканьки",
		"genres": ["movie-soviet"],
		"year": "1961"
	},
	{
		"id": 391,
		"name": "Смерть ей к лицу",
		"nameOrig": "Death Becomes Her",
		"genres": ["movie-foreign"],
		"year": "1992"
	},
	{
		"id": 392,
		"name": "Изо всех сил",
		"nameOrig": "Over the Top",
		"genres": ["movie-foreign"],
		"year": "1987"
	},
	{
		"id": 393,
		"name": "Робокоп",
		"nameOrig": "RoboCop",
		"genres": ["movie-foreign"],
		"year": "1987"
	},
	{
		"id": 394,
		"name": "Кошмар перед Рождеством",
		"nameOrig": "The Nightmare Before Christmas",
		"genres": ["cartoon-foreign"],
		"year": "1993"
	},
	{
		"id": 395,
		"name": "Крик",
		"nameOrig": "Scream",
		"genres": ["movie-foreign"],
		"year": "1996"
	},
	{
		"id": 396,
		"name": "Клаус",
		"nameOrig": "Klaus",
		"genres": ["cartoon-foreign"],
		"year": "2019"
	},
	{
		"id": 397,
		"name": "Я худею",
		"nameOrig": "Я худею",
		"genres": ["movie-russian"],
		"year": "2018"
	},
	{
		"id": 398,
		"name": "Форма воды",
		"nameOrig": "The Shape of Water",
		"genres": ["movie-foreign"],
		"year": "2017"
	},
	{
		"id": 399,
		"name": "Достучаться до небес",
		"nameOrig": "Knockin' on Heaven's Door",
		"genres": ["movie-foreign"],
		"year": "1997"
	},
	{
		"id": 400,
		"name": "1+1",
		"nameOrig": "1+1",
		"genres": ["movie-foreign"],
		"year": "2011"
	},
	{
		"id": 401,
		"name": "Крепкий орешек",
		"nameOrig": "Die Hard",
		"genres": ["movie-soviet"],
		"year": "1968"
	},
	{
		"id": 402,
		"name": "Выживший",
		"nameOrig": "The Revenant",
		"genres": ["movie-foreign"],
		"year": "2015"
	},
	{
		"id": 403,
		"name": "Три икса",
		"nameOrig": "xXx",
		"genres": ["movie-foreign"],
		"year": "2002"
	},
	{
		"id": 404,
		"name": "Чудо",
		"nameOrig": "Wonder",
		"genres": ["movie-foreign"],
		"year": "2017"
	},
	{
		"id": 405,
		"name": "Кабельщик",
		"nameOrig": "The Cable Guy",
		"genres": ["movie-foreign"],
		"year": "1996"
	},
	{
		"id": 406,
		"name": "Скорость",
		"nameOrig": "Speed",
		"genres": ["movie-foreign"],
		"year": "1994"
	},
	{
		"id": 407,
		"name": "Кентервильское привидение",
		"nameOrig": "Кентервильское привидение",
		"genres": ["cartoon-soviet"],
		"year": "1970"
	},
	{
		"id": 408,
		"name": "Одноклассники",
		"nameOrig": "Grown Ups",
		"genres": ["movie-foreign"],
		"year": "2010"
	},
	{
		"id": 409,
		"name": "Мы из будущего",
		"nameOrig": "Мы из будущего",
		"genres": ["movie-russian"],
		"year": "2008"
	},
	{
		"id": 410,
		"name": "Почему он?",
		"nameOrig": "Why Him?",
		"genres": ["movie-foreign"],
		"year": "2016"
	},
	{
		"id": 411,
		"name": "Отпуск по обмену",
		"nameOrig": "The Holiday",
		"genres": ["movie-foreign"],
		"year": "2006"
	},
	{
		"id": 412,
		"name": "Пассажиры",
		"nameOrig": "Passengers",
		"genres": ["movie-foreign"],
		"year": "2016"
	},
	{
		"id": 413,
		"name": "Колесо чудес",
		"nameOrig": "Wonder Wheel",
		"genres": ["movie-foreign"],
		"year": "2017"
	},
	{
		"id": 414,
		"name": "Дождливый день в Нью-Йорке",
		"nameOrig": "A Rainy Day in New York",
		"genres": ["movie-foreign"],
		"year": "2019"
	},
	{
		"id": 415,
		"name": "Люси",
		"nameOrig": "Lucy",
		"genres": ["movie-foreign"],
		"year": "2014"
	},
	{
		"id": 416,
		"name": "Нехочуха",
		"nameOrig": "Нехочуха",
		"genres": ["cartoon-soviet"],
		"year": "1986"
	},
	{
		"id": 417,
		"name": "Бременские музыканты",
		"nameOrig": "Бременские музыканты",
		"genres": ["cartoon-soviet"],
		"year": "1969"
	},
	{
		"id": 418,
		"name": "Тайна третьей планеты",
		"nameOrig": "Тайна третьей планеты",
		"genres": ["cartoon-soviet"],
		"year": "1981"
	},
	{
		"id": 419,
		"name": "Подарок для слона",
		"nameOrig": "Подарок для слона",
		"genres": ["cartoon-soviet"],
		"year": "1984"
	},
	{
		"id": 420,
		"name": "Малышка на миллион",
		"nameOrig": "Million Dollar Baby",
		"genres": ["movie-foreign"],
		"year": "2004"
	},
	{
		"id": 421,
		"name": "Сенсация",
		"nameOrig": "Scoop",
		"genres": ["movie-foreign"],
		"year": "2006"
	},
	{
		"id": 422,
		"name": "Добро пожаловать или Посторонним вход воспрещен",
		"nameOrig": "Добро пожаловать или Посторонним вход воспрещен",
		"genres": ["movie-soviet"],
		"year": "1964"
	},
	{
		"id": 423,
		"name": "Разрисованная вуаль",
		"nameOrig": "The Painted Veil",
		"genres": ["movie-foreign"],
		"year": "2006"
	},
	{
		"id": 424,
		"name": "Поймай меня, если сможешь",
		"nameOrig": "Catch Me If You Can",
		"genres": ["movie-foreign"],
		"year": "2002"
	},
	{
		"id": 425,
		"name": "Джокер",
		"nameOrig": "Joker",
		"genres": ["movie-foreign"],
		"year": "2019"
	},
	{
		"id": 426,
		"name": "Танго и Кэш",
		"nameOrig": "Tango & Cash",
		"genres": ["movie-foreign"],
		"year": "1989"
	},
	{
		"id": 427,
		"name": "Красота по-американски",
		"nameOrig": "American Beauty",
		"genres": ["movie-foreign"],
		"year": "1999"
	},
	{
		"id": 428,
		"name": "Несносные боссы",
		"nameOrig": "Horrible Bosses",
		"genres": ["movie-foreign"],
		"year": "2011"
	},
	{
		"id": 429,
		"name": "Вам письмо",
		"nameOrig": "You've Got Mail",
		"genres": ["movie-foreign"],
		"year": "1998"
	},
	{
		"id": 430,
		"name": "Игорь",
		"nameOrig": "Igor",
		"genres": ["cartoon-foreign"],
		"year": "2008"
	},
	{
		"id": 431,
		"name": "Фарго",
		"nameOrig": "Fargo",
		"genres": ["movie-foreign"],
		"year": "1995"
	},
	{
		"id": 432,
		"name": "Троя",
		"nameOrig": "Troy",
		"genres": ["movie-foreign"],
		"year": "2004"
	},
	{
		"id": 433,
		"name": "Васаби",
		"nameOrig": "Wasabi",
		"genres": ["movie-foreign"],
		"year": "2001"
	},
	{
		"id": 434,
		"name": "Типа крутые легавые",
		"nameOrig": "Hot Fuzz",
		"genres": ["movie-foreign"],
		"year": "2007"
	},
	{
		"id": 435,
		"name": "Изображая жертву",
		"nameOrig": "Изображая жертву",
		"genres": ["movie-russian"],
		"year": "2006"
	},
	{
		"id": 436,
		"name": "Общество мертвых поэтов",
		"nameOrig": "Dead Poets Society",
		"genres": ["movie-foreign"],
		"year": "1989"
	},
	{
		"id": 437,
		"name": "Текст",
		"nameOrig": "Текст",
		"genres": ["movie-russian"],
		"year": "2019"
	},
	{
		"id": 438,
		"name": "Белые люди не умеют прыгать",
		"nameOrig": "White Men Can't Jump",
		"genres": ["movie-foreign"],
		"year": "1992"
	},
	{
		"id": 439,
		"name": "Простые сложности",
		"nameOrig": "It's Complicated",
		"genres": ["movie-foreign"],
		"year": "2009"
	},
	{
		"id": 440,
		"name": "Тренер Картер",
		"nameOrig": "Coach Carter",
		"genres": ["movie-foreign"],
		"year": "2005"
	},
	{
		"id": 441,
		"name": "Круэлла",
		"nameOrig": "Cruella",
		"genres": ["movie-foreign"],
		"year": "2021"
	},
	{
		"id": 442,
		"name": "Драйв",
		"nameOrig": "Drive",
		"genres": ["movie-foreign"],
		"year": "2011"
	},
	{
		"id": 443,
		"name": "Пляж",
		"nameOrig": "The Beach",
		"genres": ["movie-foreign"],
		"year": "2000"
	},
	{
		"id": 444,
		"name": "Оружейный барон",
		"nameOrig": "Lord of War",
		"genres": ["movie-foreign"],
		"year": "2005"
	},
	{
		"id": 445,
		"name": "Знаки",
		"nameOrig": "Signs",
		"genres": ["movie-foreign"],
		"year": "2002"
	},
	{
		"id": 446,
		"name": "Заложник",
		"nameOrig": "Hostage",
		"genres": ["movie-foreign"],
		"year": "2005"
	},
	{
		"id": 447,
		"name": "Пункт назначения",
		"nameOrig": "Final Destination",
		"genres": ["movie-foreign"],
		"year": "2000"
	},
	{
		"id": 448,
		"name": "Кровью и потом: Анаболики",
		"nameOrig": "Pain & Gain",
		"genres": ["movie-foreign"],
		"year": "2013"
	},
	{
		"id": 449,
		"name": "10 причин моей ненависти",
		"nameOrig": "10 Things I Hate About You",
		"genres": ["movie-foreign"],
		"year": "1999"
	},
	{
		"id": 450,
		"name": "Идентификация Борна",
		"nameOrig": "The Bourne Identity",
		"genres": ["movie-foreign"],
		"year": "2002"
	},
	{
		"id": 451,
		"name": "Шакал",
		"nameOrig": "The Jackal",
		"genres": ["movie-foreign"],
		"year": "1997"
	},
	{
		"id": 452,
		"name": "Никто",
		"nameOrig": "Nobody",
		"genres": ["movie-foreign"],
		"year": "2021"
	},
	{
		"id": 453,
		"name": "Жизнь Дэвида Гейла",
		"nameOrig": "The Life of David Gale",
		"genres": ["movie-foreign"],
		"year": "2002"
	},
	{
		"id": 454,
		"name": "Бёрдмэн",
		"nameOrig": "Birdman",
		"genres": ["movie-foreign"],
		"year": "2014"
	},
	{
		"id": 455,
		"name": "Мышиная охота",
		"nameOrig": "Mouse Hunt",
		"genres": ["movie-foreign"],
		"year": "1997"
	},
	{
		"id": 456,
		"name": "Жизнь этого парня",
		"nameOrig": "This Boy's Life",
		"genres": ["movie-foreign"],
		"year": "1993"
	},
	{
		"id": 457,
		"name": "Жестокий ручей",
		"nameOrig": "Mean Creek",
		"genres": ["movie-foreign"],
		"year": "2004"
	},
	{
		"id": 458,
		"name": "Страшилы",
		"nameOrig": "The Frighteners",
		"genres": ["movie-foreign"],
		"year": "1996"
	},
	{
		"id": 459,
		"name": "Снежная королева",
		"nameOrig": "Снежная королева",
		"genres": ["cartoon-soviet"],
		"year": "1957"
	},
	{
		"id": 460,
		"name": "Самый быстрый Indian",
		"nameOrig": "The World's Fastest Indian",
		"genres": ["movie-foreign"],
		"year": "2005"
	},
	{
		"id": 461,
		"name": "Ангел-А",
		"nameOrig": "Angel-A",
		"genres": ["movie-foreign"],
		"year": "2005"
	},
	{
		"id": 462,
		"name": "Сказка о царе Салтане",
		"nameOrig": "Сказка о царе Салтане",
		"genres": ["cartoon-soviet"],
		"year": "1984"
	},
	{
		"id": 463,
		"name": "Мойдодыр",
		"nameOrig": "Мойдодыр",
		"genres": ["cartoon-soviet"],
		"year": "1954"
	},
	{
		"id": 464,
		"name": "Берегись автомобиля",
		"nameOrig": "Берегись автомобиля",
		"genres": ["movie-soviet"],
		"year": "1966"
	},
	{
		"id": 465,
		"name": "P.S. Я люблю тебя",
		"nameOrig": "P.S. I Love You",
		"genres": ["movie-foreign"],
		"year": "2007"
	},
	{
		"id": 466,
		"name": "Поездка в Америку",
		"nameOrig": "Coming to America",
		"genres": ["movie-foreign"],
		"year": "1988"
	},
	{
		"id": 467,
		"name": "Полночь в Париже",
		"nameOrig": "Midnight in Paris",
		"genres": ["movie-foreign"],
		"year": "2011"
	},
	{
		"id": 468,
		"name": "Человек-паук 3: Враг в отражении",
		"nameOrig": "Spider-Man 3",
		"genres": ["movie-foreign"],
		"year": "2007"
	},
	{
		"id": 469,
		"name": "Матрица: Перезагрузка",
		"nameOrig": "The Matrix Reloaded",
		"genres": ["movie-foreign"],
		"year": "2003"
	},
	{
		"id": 470,
		"name": "Челюсти",
		"nameOrig": "Jaws",
		"genres": ["movie-foreign"],
		"year": "1975"
	},
	{
		"id": 471,
		"name": "Прибытие",
		"nameOrig": "Arrival",
		"genres": ["movie-foreign"],
		"year": "2016"
	},
	{
		"id": 472,
		"name": "Оппенгеймер",
		"nameOrig": "Oppenheimer",
		"genres": ["movie-foreign"],
		"year": "2023"
	},
	{
		"id": 473,
		"name": "Мастер и Маргарита",
		"nameOrig": "Мастер и Маргарита",
		"genres": ["movie-russian"],
		"year": "2024"
	},
	{
		"id": 474,
		"name": "Поцелуй на вылет",
		"nameOrig": "Kiss Kiss Bang Bang",
		"genres": ["movie-foreign"],
		"year": "2005"
	},
	{
		"id": 475,
		"name": "Люди в черном",
		"nameOrig": "Men in Black",
		"genres": ["movie-foreign"],
		"year": "1997"
	},
	{
		"id": 476,
		"name": "Приключения Васи Куролесова",
		"nameOrig": "Приключения Васи Куролесова",
		"genres": ["cartoon-soviet"],
		"year": "1981"
	},
	{
		"id": 477,
		"name": "Невероятные приключения итальянцев в России",
		"nameOrig": "Невероятные приключения итальянцев в России",
		"genres": ["movie-soviet"],
		"year": "1973"
	},
	{
		"id": 478,
		"name": "Kingsman: Секретная служба",
		"nameOrig": "Kingsman: The Secret Service",
		"genres": ["movie-foreign"],
		"year": "2015"
	},
	{
		"id": 479,
		"name": "Остров сокровищ",
		"nameOrig": "Остров сокровищ",
		"genres": ["cartoon-soviet"],
		"year": "1988"
	},
	{
		"id": 480,
		"name": "Лягушка-путешественница",
		"nameOrig": "Лягушка-путешественница",
		"genres": ["cartoon-soviet"],
		"year": "1965"
	},
	{
		"id": 481,
		"name": "Впритык",
		"nameOrig": "Due Date",
		"genres": ["movie-foreign"],
		"year": "2010"
	},
	{
		"id": 482,
		"name": "Молодой человек",
		"nameOrig": "Молодой человек",
		"genres": ["movie-russian"],
		"year": "2022"
	},
	{
		"id": 483,
		"name": "Хардкор",
		"nameOrig": "Хардкор",
		"genres": ["movie-russian"],
		"year": "2016"
	},
	{
		"id": 484,
		"name": "Дикая",
		"nameOrig": "Wild",
		"genres": ["movie-foreign"],
		"year": "2014"
	},
	{
		"id": 485,
		"name": "Алеша Попович и Тугарин Змей",
		"nameOrig": "Алеша Попович и Тугарин Змей",
		"genres": ["cartoon-russian"],
		"year": "2004"
	},
	{
		"id": 486,
		"name": "Добрыня Никитич и Змей Горыныч",
		"nameOrig": "Добрыня Никитич и Змей Горыныч",
		"genres": ["cartoon-russian"],
		"year": "2006"
	},
	{
		"id": 487,
		"name": "Илья Муромец и Соловей Разбойник",
		"nameOrig": "Илья Муромец и Соловей Разбойник",
		"genres": ["cartoon-russian"],
		"year": "2007"
	},
	{
		"id": 488,
		"name": "Университет монстров",
		"nameOrig": "Monsters University",
		"genres": ["cartoon-foreign"],
		"year": "2013"
	},
	{
		"id": 489,
		"name": "Храбрая сердцем",
		"nameOrig": "Brave",
		"genres": ["cartoon-foreign"],
		"year": "2012"
	},
	{
		"id": 490,
		"name": "Ранго",
		"nameOrig": "Rango",
		"genres": ["cartoon-foreign"],
		"year": "2011"
	},
	{
		"id": 491,
		"name": "Три богатыря и Шамаханская царица",
		"nameOrig": "Три богатыря и Шамаханская царица",
		"genres": ["cartoon-russian"],
		"year": "2010"
	},
	{
		"id": 492,
		"name": "Поезд на Юму",
		"nameOrig": "3:10 to Yuma",
		"genres": ["movie-foreign"],
		"year": "2007"
	},
	{
		"id": 493,
		"name": "Привидение",
		"nameOrig": "Ghost",
		"genres": ["movie-foreign"],
		"year": "1990"
	},
	{
		"id": 494,
		"name": "Дюна",
		"nameOrig": "Dune: Part One",
		"genres": ["movie-foreign"],
		"year": "2021"
	},
	{
		"id": 495,
		"name": "Ловушка для родителей",
		"nameOrig": "The Parent Trap",
		"genres": ["movie-foreign"],
		"year": "1998"
	},
	{
		"id": 496,
		"name": "Пушки Акимбо",
		"nameOrig": "Guns Akimbo",
		"genres": ["movie-foreign"],
		"year": "2019"
	},
	{
		"id": 497,
		"name": "Убить пересмешника",
		"nameOrig": "To Kill a Mockingbird",
		"genres": ["movie-foreign"],
		"year": "1962"
	},
	{
		"id": 498,
		"name": "Аватар: Путь воды",
		"nameOrig": "Avatar: The Way of Water",
		"genres": ["movie-foreign"],
		"year": "2022"
	},
	{
		"id": 499,
		"name": "Чарли и шоколадная фабрика",
		"nameOrig": "Charlie and the Chocolate Factory",
		"genres": ["movie-foreign"],
		"year": "2005"
	},
	{
		"id": 500,
		"name": "Невыносимая тяжесть огромного таланта",
		"nameOrig": "The Unbearable Weight of Massive Talent",
		"genres": ["movie-foreign"],
		"year": "2022"
	},
	{
		"id": 501,
		"name": "Чего хотят женщины",
		"nameOrig": "What Women Want",
		"genres": ["movie-foreign"],
		"year": "2000"
	},
	{
		"id": 502,
		"name": "Мотылёк",
		"nameOrig": "Papillon",
		"genres": ["movie-foreign"],
		"year": "2017"
	},
	{
		"id": 503,
		"name": "Лето 84",
		"nameOrig": "Summer of 84",
		"genres": ["movie-foreign"],
		"year": "2017"
	},
	{
		"id": 504,
		"name": "Развод по-американски",
		"nameOrig": "The Break-Up",
		"genres": ["movie-foreign"],
		"year": "2006"
	},
	{
		"id": 505,
		"name": "Последний рубеж",
		"nameOrig": "Homefront",
		"genres": ["movie-foreign"],
		"year": "2013"
	},
	{
		"id": 506,
		"name": "Девушка с татуировкой дракона",
		"nameOrig": "The Girl with the Dragon Tattoo",
		"genres": ["movie-foreign"],
		"year": "2011"
	},
	{
		"id": 507,
		"name": "Ведьмина служба доставки",
		"nameOrig": "Majo no Takkyuubin",
		"genres": ["cartoon-foreign"],
		"year": "1989"
	},
	{
		"id": 508,
		"name": "Цена страсти",
		"nameOrig": "The Ledge",
		"genres": ["movie-foreign"],
		"year": "2011"
	},
	{
		"id": 509,
		"name": "Приключения Паддингтона",
		"nameOrig": "Paddington",
		"genres": ["movie-foreign"],
		"year": "2014"
	},
	{
		"id": 510,
		"name": "Завод",
		"nameOrig": "Завод",
		"genres": ["movie-russian"],
		"year": "2018"
	},
	{
		"id": 511,
		"name": "Человек, который изменил всё",
		"nameOrig": "Moneyball",
		"genres": ["movie-foreign"],
		"year": "2011"
	},
	{
		"id": 512,
		"name": "Одиннадцать друзей Оушена",
		"nameOrig": "Ocean's Eleven",
		"genres": ["movie-foreign"],
		"year": "2001"
	},
	{
		"id": 513,
		"name": "Джиперс Криперс",
		"nameOrig": "Jeepers Creepers",
		"genres": ["movie-foreign"],
		"year": "2001"
	},
	{
		"id": 514,
		"name": "Основатель",
		"nameOrig": "The Founder",
		"genres": ["movie-foreign"],
		"year": "2016"
	},
	{
		"id": 515,
		"name": "Пиджак",
		"nameOrig": "The Jacket",
		"genres": ["movie-foreign"],
		"year": "2004"
	},
	{
		"id": 516,
		"name": "Амели",
		"nameOrig": "Le Fabuleux destin d'Amélie Poulain",
		"genres": ["movie-foreign"],
		"year": "2001"
	},
	{
		"id": 517,
		"name": "Мимино",
		"nameOrig": "Мимино",
		"genres": ["movie-soviet"],
		"year": "1977"
	},
	{
		"id": 518,
		"name": "Воздушный маршал",
		"nameOrig": "Non-Stop",
		"genres": ["movie-foreign"],
		"year": "2014"
	},
	{
		"id": 519,
		"name": "Свадебный переполох",
		"nameOrig": "The Wedding Planner",
		"genres": ["movie-foreign"],
		"year": "2001"
	},
	{
		"id": 520,
		"name": "Земля до начала времен",
		"nameOrig": "The Land Before Time",
		"genres": ["cartoon-foreign"],
		"year": "1988"
	},
	{
		"id": 521,
		"name": "Бриллиантовый полицейский",
		"nameOrig": "Blue Streak",
		"genres": ["movie-foreign"],
		"year": "1999"
	},
	{
		"id": 522,
		"name": "Дэдпул и Росомаха",
		"nameOrig": "Deadpool and Wolverine",
		"genres": ["movie-foreign"],
		"year": "2024"
	},
	{
		"id": 523,
		"name": "Вызов",
		"nameOrig": "Вызов",
		"genres": ["movie-russian"],
		"year": "2023"
	},
	{
		"id": 524,
		"name": "Три богатыря на дальних берегах",
		"nameOrig": "Три богатыря на дальних берегах",
		"genres": ["cartoon-russian"],
		"year": "2012"
	},
	{
		"id": 525,
		"name": "Три богатыря: Ход конем",
		"nameOrig": "Три богатыря: Ход конем",
		"genres": ["cartoon-russian"],
		"year": "2014"
	},
	{
		"id": 526,
		"name": "Три богатыря и Морской царь",
		"nameOrig": "Три богатыря и Морской царь",
		"genres": ["cartoon-russian"],
		"year": "2016"
	},
	{
		"id": 527,
		"name": "Фоллаут",
		"nameOrig": "Fallout",
		"genres": ["series-foreign"],
		"year": "2024"
	},
	{
		"id": 528,
		"name": "Уэнсдэй",
		"nameOrig": "Wednesday",
		"genres": ["series-foreign"],
		"year": "2022"
	},
	{
		"id": 529,
		"name": "Одни из нас",
		"nameOrig": "The Last of Us",
		"genres": ["series-foreign"],
		"year": "2023"
	},
	{
		"id": 530,
		"name": "Князь Владимир",
		"nameOrig": "Князь Владимир",
		"genres": ["cartoon-russian"],
		"year": "2006"
	},
	{
		"id": 531,
		"name": "Секретные материалы",
		"nameOrig": "The X Files",
		"genres": ["series-foreign"],
		"year": "1993 - 2018"
	},
	{
		"id": 532,
		"name": "Зачарованные",
		"nameOrig": "Charmed",
		"genres": ["series-foreign"],
		"year": "1998 - 2006"
	},
	{
		"id": 533,
		"name": "Обратная сторона Луны",
		"nameOrig": "Обратная сторона Луны",
		"genres": ["series-russian"],
		"year": "2012 - 2016"
	},
	{
		"id": 534,
		"name": "Метод",
		"nameOrig": "Метод",
		"genres": ["series-russian"],
		"year": "2015 - 2020"
	},
	{
		"id": 535,
		"name": "Ворошиловский стрелок",
		"nameOrig": "Ворошиловский стрелок",
		"genres": ["movie-russian"],
		"year": "1999"
	},
	{
		"id": 536,
		"name": "Особенности национальной охоты",
		"nameOrig": "Особенности национальной охоты",
		"genres": ["movie-russian"],
		"year": "1995"
	},
	{
		"id": 537,
		"name": "Ширли-мырли",
		"nameOrig": "Ширли-мырли",
		"genres": ["movie-russian"],
		"year": "1995"
	},
	{
		"id": 538,
		"name": "Лука",
		"nameOrig": "Luca",
		"genres": ["cartoon-foreign"],
		"year": "2021"
	},
	{
		"id": 539,
		"name": "Человек-паук: Паутина вселенных",
		"nameOrig": "Spider-Man: Across the Spider-Verse",
		"genres": ["cartoon-foreign"],
		"year": "2023"
	},
	{
		"id": 540,
		"name": "Головоломка 2",
		"nameOrig": "Inside Out 2",
		"genres": ["cartoon-foreign"],
		"year": "2024"
	},
	{
		"id": 541,
		"name": "Роботы",
		"nameOrig": "Robots",
		"genres": ["cartoon-foreign"],
		"year": "2005"
	},
	{
		"id": 542,
		"name": "Леон",
		"nameOrig": "Leon",
		"genres": ["movie-foreign"],
		"year": "1994"
	},
	{
		"id": 543,
		"name": "Поехавшая",
		"nameOrig": "Поехавшая",
		"genres": ["movie-russian"],
		"year": "2023"
	},
	{
		"id": 544,
		"name": "Приключения Паддингтона 2",
		"nameOrig": "Paddington 2",
		"genres": ["movie-foreign"],
		"year": "2017"
	},
	{
		"id": 545,
		"name": "Я, снова я и Ирэн",
		"nameOrig": "Me, Myself & Irene",
		"genres": ["movie-foreign"],
		"year": "2000"
	},
	{
		"id": 546,
		"name": "Первобытный страх",
		"nameOrig": "Primal Fear",
		"genres": ["movie-foreign"],
		"year": "1996"
	},
	{
		"id": 547,
		"name": "Дневник Бриджит Джонс",
		"nameOrig": "Bridget Jones's Diary",
		"genres": ["movie-foreign"],
		"year": "2001"
	},
	{
		"id": 548,
		"name": "Матч поинт",
		"nameOrig": "Match Point",
		"genres": ["movie-foreign"],
		"year": "2005"
	},
	{
		"id": 549,
		"name": "Мистер Мерседес",
		"nameOrig": "Mr. Mercedes",
		"genres": ["series-foreign"],
		"year": "2017 - 2019"
	},
	{
		"id": 550,
		"name": "Приключения желтого чемоданчика",
		"nameOrig": "Приключения желтого чемоданчика",
		"genres": ["movie-soviet"],
		"year": "1970"
	},
	{
		"id": 551,
		"name": "Усатый нянь",
		"nameOrig": "Усатый нянь",
		"genres": ["movie-soviet"],
		"year": "1977"
	}


















]
